aryzer/__init__.py
aryzer/aryzer.py
aryzer-0.0.2.dist-info/METADATA
aryzer-0.0.2.dist-info/WHEEL
aryzer-0.0.2.dist-info/licenses/LICENSE
aryzer-0.0.2.dist-info/RECORD
