Metadata-Version: 2.1
Name: aryzer
Version: 0.0.2
Summary: Learn from trainingsdata a classifier to label article
Project-URL: Homepage, https://gitup.uni-potsdam.de/innohs/train-articleclassifier
Project-URL: Bug Tracker, https://gitup.uni-potsdam.de/innohs/train-articleclassifier/-/issues
Author-email: Jan Bernoth <jan.bernoth@uni-potsdam.de>
License-File: LICENSE
Classifier: License :: OSI Approved :: MIT License
Classifier: Operating System :: OS Independent
Classifier: Programming Language :: Python :: 3
Requires-Python: >=3.7
Requires-Dist: matplotlib>=3.6.2
Requires-Dist: numpy>=1.23.5
Requires-Dist: pandas>=1.5.2
Requires-Dist: scikit-learn>=1.1.3
Requires-Dist: seaborn>=0.12.1
Requires-Dist: setuptools>=60.2.0
